[[{"ID": "0"}, {"code": "BASLENAH"}, {"description": "Basin length from outlet to basin divide determined using the method in the ArcHydro Toolset"}, {"name": "Basin Length ArcHydro Method"}, {"unit": "miles"}, {"value": "34.61"}], [{"ID": "0"}, {"code": "BFI"}, {"description": "Proportion of mean annual flow that is from ground water (base flow)"}, {"name": "Base Flow Index"}, {"unit": "dimensionless"}, {"value": "0.546695"}], [{"ID": "0"}, {"code": "BSHAPE"}, {"description": "Basin Shape Factor for Area"}, {"name": "Basin Shape Factor"}, {"unit": "dimensionless"}, {"value": "5.33"}], [{"ID": "0"}, {"code": "BSLDEM10M"}, {"description": "Mean basin slope computed from 10 m DEM"}, {"name": "Mean Basin Slope from 10m DEM"}, {"unit": "percent"}, {"value": "1.96"}], [{"ID": "0"}, {"code": "CCM"}, {"description": "Constant of channel maintenance computed as drainage area divided by total stream length"}, {"name": "Constant of Channel Maintenance"}, {"unit": "square mile per mile"}, {"value": "0.89"}], [{"ID": "0"}, {"code": "CSL100"}, {"description": "Longest flow path slope in feet per miles, using DEM"}, {"name": "Longest flow path slope in feet per miles"}, {"unit": "feet per mi"}, {"value": "4.71"}], [{"ID": "0"}, {"code": "CSL10_85"}, {"description": "Change in elevation divided by length between points 10 and 85 percent of distance along main channel to basin divide - main channel method not known"}, {"name": "Stream Slope 10 and 85 Method"}, {"unit": "feet per mi"}, {"value": "3.87"}], [{"ID": "0"}, {"code": "DESMOIN"}, {"description": "Area underlain by Des Moines Lobe"}, {"name": "Des Moines Lobe"}, {"unit": "percent"}, {"value": "100.0"}], [{"ID": "0"}, {"code": "DRNAREA"}, {"description": "Area that drains to a point on a stream"}, {"name": "Drainage Area"}, {"unit": "square miles"}, {"value": "225.0"}], [{"ID": "0"}, {"code": "DRNFREQ"}, {"description": "Number of first order streams per square mile of drainage area"}, {"name": "Drainage Frequency"}, {"unit": "1st-order streams per square mile"}, {"value": "0.6"}], [{"ID": "0"}, {"code": "FOSTREAM"}, {"description": "Number of First Order Streams"}, {"name": "Number of First Order Streams"}, {"unit": "dimensionless"}, {"value": "135.0"}], [{"ID": "0"}, {"code": "HIGHREG"}, {"description": "HIGHREG"}, {"name": "HIGHREG"}, {"unit": "dimensionless"}, {"value": "1.0"}], [{"ID": "0"}, {"code": "HYSEP"}, {"description": "Median percentage of baseflow to annual streamflow"}, {"name": "Hydrograph separation percent"}, {"unit": "percent"}, {"value": "55.27"}], [{"ID": "0"}, {"code": "I24H10Y"}, {"description": "Maximum 24-hour precipitation that occurs on average once in 10 years"}, {"name": "24 Hour 10 Year Precipitation"}, {"unit": "inches"}, {"value": "4.4"}], [{"ID": "0"}, {"code": "LC11CRPHAY"}, {"description": "Percentage of cultivated crops and hay, classes 81 and 82, from NLCD 2011"}, {"name": "Percent_Crops_and_Hay_from_NLCD2011"}, {"unit": "percent"}, {"value": "88.4"}], [{"ID": "0"}, {"code": "LC11DEV"}, {"description": "Percentage of developed (urban) land from NLCD 2011 classes 21-24"}, {"name": "Percent Developed from NLCD2011"}, {"unit": "percent"}, {"value": "6.71"}], [{"ID": "0"}, {"code": "LC11IMP"}, {"description": "Average percentage of impervious area determined from NLCD 2011 impervious dataset"}, {"name": "Percent_Impervious_NLCD2011"}, {"unit": "percent"}, {"value": "0.84"}], [{"ID": "0"}, {"code": "PRECIP"}, {"description": "Mean Annual Precipitation"}, {"name": "Mean Annual Precipitation"}, {"unit": "inches"}, {"value": "33.91"}], [{"ID": "0"}, {"code": "PRJULDEC10"}, {"description": "Basin average mean precipitation for July to December from PRISM 1981-2010"}, {"name": "Basin_Ave_Precip_Jul_Dec_PRISM_2010"}, {"unit": "inches"}, {"value": "2.89"}], [{"ID": "0"}, {"code": "RSD"}, {"description": "Relative stream density first defined in SIR 2012_5171"}, {"name": "Relative Stream Density"}, {"unit": "dimensionless"}, {"value": "0.47"}], [{"ID": "0"}, {"code": "SSURGOA"}, {"description": "Percentage of area of Hydrologic Soil Type A from SSURGO"}, {"name": "SSURGO Percent Hydrologic Soil Type A"}, {"unit": "percent"}, {"value": "1.05"}], [{"ID": "0"}, {"code": "SSURGOB"}, {"description": "Percentage of area of Hydrologic Soil Type B from SSURGO"}, {"name": "SSURGO Percent Hydrologic Soil Type B"}, {"unit": "percent"}, {"value": "98.4"}], [{"ID": "0"}, {"code": "SSURGOC"}, {"description": "Percentage of area of Hydrologic Soil Type C from SSURGO"}, {"name": "SSURGO Percent Hydrologic Soil Type C"}, {"unit": "percent"}, {"value": "0.55"}], [{"ID": "0"}, {"code": "SSURGOD"}, {"description": "Percentage of area of Hydrologic Soil Type D from SSURGO"}, {"name": "SSURGO Percent Hydrologic Soil Type D"}, {"unit": "percent"}, {"value": "0.0"}], [{"ID": "0"}, {"code": "SSURGOKSAT"}, {"description": "Saturated hydraulic conductivity in micrometers per second from NRCS SSURGO database"}, {"name": "SSURGO Saturated Hydraulic Conductivity"}, {"unit": "micrometers per second"}, {"value": "10.12"}], [{"ID": "0"}, {"code": "STREAM_VARG"}, {"description": "Streamflow variability index as defined in WRIR 02-4068, computed from regional grid"}, {"name": "Streamflow Variability Index from Grid"}, {"unit": "dimensionless"}, {"value": "0.61"}], [{"ID": "0"}, {"code": "STRMTOT"}, {"description": "total length of all mapped streams (1:24,000-scale) in the basin"}, {"name": "Stream Length Total"}, {"unit": "miles"}, {"value": "252.815"}], [{"ID": "0"}, {"code": "TAU_ANN_G"}, {"description": "Tau, Average annual base-flow recession time constant as defined in SIR 2008-5065"}, {"name": "Tau Annual from Grid"}, {"unit": "days"}, {"value": "21.15"}]]